recon_comp/__init__.py
recon_comp/recon_comp.py
recon_comp-0.0.1.dist-info/METADATA
recon_comp-0.0.1.dist-info/WHEEL
recon_comp-0.0.1.dist-info/top_level.txt
recon_comp-0.0.1.dist-info/RECORD
