Metadata-Version: 2.1
Name: recon_comp
Version: 0.0.1
Summary: A recon module to compare two databases in UC
Author-email: rohan goel <rohan.goel@databricks.com>
Requires-Dist: pyspark
Requires-Dist: pandas
